[
  {
    "name": "Newsletter Subscribers",
    "description": "People who subscribed to the newsletter",
    "id": 1,
    "createdAt": "2025-04-18T02:19:28.299Z",
    "updatedAt": "2025-04-18T02:19:28.299Z"
  },
  {
    "name": "Product Updates",
    "description": "People interested in product updates",
    "id": 2,
    "createdAt": "2025-04-18T02:19:28.300Z",
    "updatedAt": "2025-04-18T02:19:28.300Z"
  },
  {
    "name": "New Customers",
    "description": "Recently acquired customers",
    "id": 3,
    "createdAt": "2025-04-18T02:19:28.300Z",
    "updatedAt": "2025-04-18T02:19:28.300Z"
  },
  {
    "name": "VIP Members",
    "description": "Premium customers",
    "id": 4,
    "createdAt": "2025-04-18T02:19:28.300Z",
    "updatedAt": "2025-04-18T02:19:28.300Z"
  }
]